InfinityStoreLib/Discord/Uploader.py
InfinityStoreLib/Discord/__init__.py
InfinityStoreLib/Discord/cannels.yaml
infinitystorelib-0.0.1.dist-info/METADATA
infinitystorelib-0.0.1.dist-info/WHEEL
infinitystorelib-0.0.1.dist-info/licenses/LICENSE
infinitystorelib-0.0.1.dist-info/RECORD
