Metadata-Version: 2.4
Name: InfinityStoreLib
Version: 0.0.1
Author: Fabota51
License: MIT
License-File: LICENSE
Keywords: Discord,Infinity,Python,Storage,Uploader
Classifier: Operating System :: OS Independent
Classifier: Programming Language :: Python :: 3
Requires-Python: >=3.9
Requires-Dist: faker>=37.11.0
Requires-Dist: pyaescrypt>=6.1.1
Requires-Dist: pyyaml>=6.0.3
Requires-Dist: requests>=2.32.5
